setup.cfg
setup.py
pybattlerite/__init__.py
pybattlerite/asyncclient.py
pybattlerite/client.py
pybattlerite/clientbase.py
pybattlerite/errors.py
pybattlerite/models.py
pybattlerite/utils.py
pybattlerite.egg-info/PKG-INFO
pybattlerite.egg-info/SOURCES.txt
pybattlerite.egg-info/dependency_links.txt
pybattlerite.egg-info/requires.txt
pybattlerite.egg-info/top_level.txt
pybattlerite/data/gameplay.json
pybattlerite/data/stackables.json
pybattlerite/data/localization/Brazilian.ini
pybattlerite/data/localization/English.ini
pybattlerite/data/localization/French.ini
pybattlerite/data/localization/German.ini
pybattlerite/data/localization/Italian.ini
pybattlerite/data/localization/Japanese.ini
pybattlerite/data/localization/Korean.ini
pybattlerite/data/localization/Polish.ini
pybattlerite/data/localization/Romanian.ini
pybattlerite/data/localization/Russian.ini
pybattlerite/data/localization/SChinese.ini
pybattlerite/data/localization/Spanish.ini
pybattlerite/data/localization/Turkish.ini