Metadata-Version: 1.2
Name: pybattlerite
Version: 0.5.18
Summary: A wrapper for the madglory Battlerite API, complete with synchronous and asynchronous client implementations.
Home-page: https://github.com/xKynn/PyBattlerite
Author: xKynn
Author-email: xkynn@github.com
License: UNKNOWN
Download-URL: https://github.com/xKynn/PyBattlerite/archive/0.5.18.tar.gz
Keywords: battlerite,asyncbattlerite,async-battlerite,async_battlerite
Platform: UNKNOWN
Requires-Python: >=3.5
